{
  "timestamp": "2026-03-18T21:51:48.006192",
  "batch_size": 4,
  "runs": [
    {
      "id": "20260318_215148_000",
      "language": "javascript",
      "problem": "LRU cache implementation",
      "code_length": 244,
      "file": "20260318_215148_000_javascript_LRU_cache_implementation.js",
      "complexity": {
        "time": "O(n)",
        "space": "O(1)"
      },
      "status": "success"
    },
    {
      "id": "20260318_215148_001",
      "language": "python",
      "problem": "binary tree traversal (BFS/DFS)",
      "code_length": 306,
      "file": "20260318_215148_001_python_binary_tree_traversal_BFS_DFS.py",
      "complexity": {
        "time": "O(n)",
        "space": "O(1)"
      },
      "status": "success"
    },
    {
      "id": "20260318_215148_002",
      "language": "rust",
      "problem": "stack with min() in O(1)",
      "code_length": 220,
      "file": "20260318_215148_002_rust_stack_with_min_in_O1.rs",
      "complexity": {
        "time": "O(n)",
        "space": "O(1)"
      },
      "status": "success"
    },
    {
      "id": "20260318_215148_003",
      "language": "c",
      "problem": "A* pathfinding algorithm",
      "code_length": 246,
      "file": "20260318_215148_003_c_A*_pathfinding_algorithm.c",
      "complexity": {
        "time": "O(n)",
        "space": "O(1)"
      },
      "status": "success"
    }
  ]
}