{
  "timestamp": "2026-03-20T20:59:20.665653",
  "batch_size": 4,
  "runs": [
    {
      "id": "20260320_205920_000",
      "language": "python",
      "problem": "2FA TOTP generator",
      "code_length": 293,
      "file": "20260320_205920_000_python_2FA_TOTP_generator.py",
      "complexity": {
        "time": "O(n)",
        "space": "O(1)"
      },
      "status": "success"
    },
    {
      "id": "20260320_205920_001",
      "language": "go",
      "problem": "TCP port scanner",
      "code_length": 198,
      "file": "20260320_205920_001_go_TCP_port_scanner.go",
      "complexity": {
        "time": "O(n)",
        "space": "O(1)"
      },
      "status": "success"
    },
    {
      "id": "20260320_205920_002",
      "language": "rust",
      "problem": "Password strength checker",
      "code_length": 221,
      "file": "20260320_205920_002_rust_Password_strength_checker.rs",
      "complexity": {
        "time": "O(n)",
        "space": "O(1)"
      },
      "status": "success"
    },
    {
      "id": "20260320_205920_003",
      "language": "go",
      "problem": "Cron expression parser",
      "code_length": 204,
      "file": "20260320_205920_003_go_Cron_expression_parser.go",
      "complexity": {
        "time": "O(n)",
        "space": "O(1)"
      },
      "status": "success"
    }
  ]
}